databridgex/__init__.py
databridgex-0.0.0.dist-info/METADATA
databridgex-0.0.0.dist-info/WHEEL
databridgex-0.0.0.dist-info/top_level.txt
databridgex-0.0.0.dist-info/RECORD
