Metadata-Version: 2.1
Name: databridgex
Version: 0.0.0
Summary: Coming soon
Author-email: databridgex <you@example.com>
